{
  "M10Robot:ProtectiveShell": {
    "NAME": "Protective Shell",
    "FLAVOR": "Not to be confused with Reflective Shell",
    "DESCRIPTIONS": [
      "At the start of each combat, gain #b"," #ym10robot:Protect.",
      "Damage mitigated: "," NL Scrambles: "
    ]
  },
  "M10Robot:ProtectiveShell": {
    "NAME": "ProtectiveShell 2.0",
    "FLAVOR": "The upgraded shell can withstand additional hits over its predecessor.",
    "DESCRIPTIONS": [
      "At the start of each combat, gain #b"," #ym10robot:Protect.",
      "Damage mitigated: "," NL Scrambles: "
    ]
  },
  "M10Robot:BottledStar": {
    "NAME": "Bottled Star",
    "FLAVOR": "Now you can watch for shooting stars whenever you wish.",
    "DESCRIPTIONS": [
      "Upon pickup, choose a card. Whenever you play this card, deal #b5 damage to ALL enemies.",
      "Choose a card for ",
      "Whenever you play ",", deal #b5 damage to ALL enemies.",
      "Damage dealt: "," NL Per combat: "," NL Per turn: "
    ]
  },
  "M10Robot:ModularBody": {
    "NAME": "Modular Body",
    "FLAVOR": "So much room for customization!",
    "DESCRIPTIONS": [
      "Start each combat with #b"," #ym10robot:Module slots."
    ]
  }
}